pandasai_local/__init__.py
pandasai_local/local_llm.py
pandasai_local-0.1.5.dist-info/METADATA
pandasai_local-0.1.5.dist-info/WHEEL
pandasai_local-0.1.5.dist-info/RECORD
